flowmeter/__init__.py
flowmeter/flowmeter.py
flowmeter-0.0.2.dist-info/LICENSE
flowmeter-0.0.2.dist-info/METADATA
flowmeter-0.0.2.dist-info/WHEEL
flowmeter-0.0.2.dist-info/top_level.txt
flowmeter-0.0.2.dist-info/RECORD
